spm_hris_client/__init__.py
spm_hris_client/client.py
hris_client-0.1.0.dist-info/METADATA
hris_client-0.1.0.dist-info/WHEEL
hris_client-0.1.0.dist-info/top_level.txt
hris_client-0.1.0.dist-info/RECORD
